{"assets/Logo.svg":["assets/logo/Logo.svg"],"assets/extras/Drawer_Button.png":["assets/extras/Drawer_Button.png"],"assets/extras/double_quotes.svg":["assets/extras/double_quotes.svg"],"assets/extras/person.png":["assets/extras/person.png"],"assets/gallery/gallery1.jpg":["assets/gallery/gallery1.jpg"],"assets/gallery/gallery4.png":["assets/gallery/gallery4.png"],"assets/gallery/room.jpg":["assets/gallery/room.jpg"],"assets/images/Location_Image.png":["assets/images/Location_Image.png"],"assets/logo/DSC_logo.png":["assets/logo/DSC_logo.png"],"assets/logo/Fb.png":["assets/logo/Fb.png"],"assets/logo/Insta.png":["assets/logo/Insta.png"],"assets/logo/Logo.png":["assets/logo/Logo.png"],"assets/logo/Logo.svg":["assets/logo/Logo.svg"],"assets/logo/beach.png":["assets/logo/beach.png"],"assets/logo/palm.png":["assets/logo/palm.png"],"assets/video/nature.mp4":["assets/video/nature.mp4"],"fonts/FjallaOne-Regular.ttf":["fonts/FjallaOne-Regular.ttf"],"fonts/Oswald-Regular.ttf":["fonts/Oswald-Regular.ttf"],"fonts/Pacifico-Regular.ttf":["fonts/Pacifico-Regular.ttf"],"fonts/Social_Media_Icons.ttf":["fonts/Social_Media_Icons.ttf"],"packages/cupertino_icons/assets/CupertinoIcons.ttf":["packages/cupertino_icons/assets/CupertinoIcons.ttf"]}